mcfetch/__init__.py
mcfetch/asyncmcfetch.py
mcfetch/exceptions.py
mcfetch/mcfetch.py
mcfetch/tools.py
mcfetch-2.1.3.dist-info/licenses/LICENSE
tests/__init__.py
tests/test_async_fetch_player.py
tests/test_fetch_player.py
tests/test_tools.py
mcfetch-2.1.3.dist-info/METADATA
mcfetch-2.1.3.dist-info/WHEEL
mcfetch-2.1.3.dist-info/top_level.txt
mcfetch-2.1.3.dist-info/RECORD
