Metadata-Version: 2.4
Name: mcfetch
Version: 2.1.3
Summary: Modified version of mcuuid - fetches Minecraft player information from the Mojang API
Home-page: https://github.com/Luciism/mcfetch
Author: clerie, Lucism
Author-email: contact@lucism.dev
Classifier: Programming Language :: Python :: 3
Classifier: License :: OSI Approved :: MIT License
Classifier: Operating System :: OS Independent
License-File: LICENSE
Requires-Dist: requests>=2.31.0
Requires-Dist: aiohttp>=3.9.4
Requires-Dist: aiohttp_client_cache>=0.8.1
Dynamic: author
Dynamic: author-email
Dynamic: classifier
Dynamic: description
Dynamic: description-content-type
Dynamic: home-page
Dynamic: license-file
Dynamic: requires-dist
Dynamic: summary
